<?xml version="1.0" encoding="utf-8" ?>
<import name="APPL1_MAP">
  <queues total="5" bulksize="4000" errorthreshold="1000" />
  <source location="#InstructionConfig#\APPL1" isxml="0" delimiter="|" queuefirst="0" rootpath="" />
  <destination server="0025dtmjones.woodforest.net" database="Archon" entity="APPL1"
    truncate="1" dropindexes="1" />
  <mappings>
    <map index="0" column="Z_ID" filecolumn="REC.ID" ignore="0" />
    <map index="1" column="ACCT" filecolumn="ACCT NUM" ignore="0" />
    <map index="2" column="APPL" filecolumn="APPL" ignore="0" />
    <map index="3" column="AVG_COL_CURR" filecolumn="AVG COL CURR MON" ignore="0" />
    <map index="4" column="BEG_BAL_LSTT" filecolumn="BEG BAL LAST STMT" ignore="0" />
    <map index="5" column="BEG_STT_DT_LSTT" filecolumn="BEG STMT PREV DAT" ignore="0" />
    <map index="6" column="CIF_SEQ" filecolumn="OWNER CIF SEQ" ignore="0" />
    <map index="7" column="CLASS" filecolumn="CLASS CODE" ignore="0" />
    <map index="8" column="CTD_CR_AMT_LSTT" filecolumn="CTD CREDIT AMOUNTLSTT" ignore="0" />
    <map index="9" column="CTD_DB_AMT_LSTT" filecolumn="CTD DEBIT AMOUNTLSTT" ignore="0" />
    <map index="10" column="FED_CATEGORY" filecolumn="FEDERAL TAX CATEGORY" ignore="0" />
    <map index="11" column="LEDGER_BAL" filecolumn="LEDGER BAL" ignore="0" />
    <map index="12" column="OWNER" filecolumn="OWNER CIF NUM" ignore="0" />
    <map index="13" column="STATUS" filecolumn="STATUS" ignore="0" />
    <map index="14" column="NOTE" filecolumn="NOTE" ignore="0" />
    <map index="15" column="END_STT_DT_LSTT" filecolumn="END STMT PREV DAT" ignore="0" />
  </mappings>
</import>